{
    "name": "McAfee ESM v2",
    "description": "Run queries and receive alarms from Intel Security ESM. Support version 10 and above",
    "support": "demisto",
    "serverMinVersion": "5.0.0",
    "currentVersion": "1.0.0",
    "author": "demisto",
    "url": "https://www.demisto.com",
    "email": "",
    "categories": ["Analytics & SIEM"],
    "tags": [],
    "created": "2020-04-23T05:53:58Z",
    "updated": "2020-04-23T05:53:58Z",
    "beta": false,
    "deprecated": false,
    "certification": "certified",
    "useCases": [],
    "keywords": [],
    "dependencies": {}
}